{
    "name": "vue-storages",
    "description": "Lightweight localStorage and sessionStorage wrapper",
    "bundledDependencies": false,
    "homepage": "",
    "license": "MIT",
    "author": {
        "name": "John Pendenque"
    },
    "files": [
        "local-storage.js",
        "session-storage.js",
        "vue-storages.d.ts"
    ],
    "keywords": [
        "vue",
        "local storage",
        "session storage"
    ],
    "dependencies": {
        "@vue/devtools-api": "^6.0.0-beta.14"
    },
    "peerDependencies": {
        "vue": "^3.1.0"
    },
    "devDependencies": {
        "vue": "^3.1.0"
    },
    "repository": {
        "type": "git",
        "url": "git+https://github.com/Zadigo/vue-storages"
    },
    "bugs": {
        "url": "http://exampl.com"
    },
    "types": "vue-storages.d.ts",
    "typings": "vue-storages.d.ts",
    "version": "1.0.0"
}
